Workbook

Sheet Budget
A1: Uni of Bath Budget: October 2026 to June 2027
A2: How to use: blue text = numbers you can change. Yellow = my assumptions, so check them. Black = formulas, don't edit. Green = pulled from another cell or sheet.
A4: Settings
A5: Budget start (Monday) | B5: 46300
A6: Budget end (leave for summer) | B6: 46551
A7: Weeks in budget | B7: =ROUND((B6-B5+1)/7,0) -> 36
A8: Savings target per week (£) | B8: 25
A9: Tracker limits use plan | B9: Suggested
A11: Income
A12: Source | B12: Amount (£) | C12: Frequency | D12: Weekly (£) | E12: Period total (£) | F12: Notes
A13: SFE maintenance loan | B13: 5000 | C13: Per period | D13: =IF($C13="Weekly",B13,IF($C13="Monthly",B13*12/52,B13/$B$7)) -> 138.88889 | E13: =D13*$B$7 -> 5000 | F13: Your figure. Paid in 3 instalments (~£1,667 each: Sep, Jan, Apr).
A14: Grandparents | B14: 1000 | C14: Per period | D14: =IF($C14="Weekly",B14,IF($C14="Monthly",B14*12/52,B14/$B$7)) -> 27.777778 | E14: =D14*$B$7 -> 1000 | F14: Your figure: £1,000 for the year.
A15: Dad | B15: 24 | C15: Weekly | D15: =IF($C15="Weekly",B15,IF($C15="Monthly",B15*12/52,B15/$B$7)) -> 24 | E15: =D15*$B$7 -> 864 | F15: Your figure: £24 a week.
A16: Total income | D16: =SUM(D13:D15) -> 190.66667 | E16: =SUM(E13:E15) -> 6864
A18: Spending: your current habits vs a suggested plan
A19: Category | B19: Current amount (£) | C19: Frequency | D19: Current weekly (£) | E19: Current period total (£) | F19: Suggested amount (£) | G19: Suggested weekly (£) | H19: Suggested period total (£) | I19: Saving by June (£) | J19: In weekly tracker? | K19: How to save
A20: Groceries | B20: 70 | C20: Weekly | D20: =IF($C20="Weekly",B20,IF($C20="Monthly",B20*12/52,B20/$B$7)) -> 70 | E20: =D20*$B$7 -> 2520 | F20: 55 | G20: =IF($C20="Weekly",F20,IF($C20="Monthly",F20*12/52,F20/$B$7)) -> 55 | H20: =G20*$B$7 -> 1980 | I20: =E20-H20 -> 540 | J20: Yes | K20: Shop at Aldi/Lidl, meal-prep in batches, write a list, buy own-brand, shop yellow-sticker reductions.
A21: Laundry | B21: 10 | C21: Weekly | D21: =IF($C21="Weekly",B21,IF($C21="Monthly",B21*12/52,B21/$B$7)) -> 10 | E21: =D21*$B$7 -> 360 | F21: 7 | G21: =IF($C21="Weekly",F21,IF($C21="Monthly",F21*12/52,F21/$B$7)) -> 7 | H21: =G21*$B$7 -> 252 | I21: =E21-H21 -> 108 | J21: Yes | K21: Wash only full loads and dry on a clothes airer instead of the tumble dryer.
A22: Coffee (£3 x 7 days) | B22: 21 | C22: Weekly | D22: =IF($C22="Weekly",B22,IF($C22="Monthly",B22*12/52,B22/$B$7)) -> 21 | E22: =D22*$B$7 -> 756 | F22: 9 | G22: =IF($C22="Weekly",F22,IF($C22="Monthly",F22*12/52,F22/$B$7)) -> 9 | H22: =G22*$B$7 -> 324 | I22: =E22-H22 -> 432 | J22: Yes | K22: Have 3 bought coffees a week and make the rest at home or in halls. Bring a reusable cup for discounts.
A23: Nights out (2 x £20) | B23: 40 | C23: Weekly | D23: =IF($C23="Weekly",B23,IF($C23="Monthly",B23*12/52,B23/$B$7)) -> 40 | E23: =D23*$B$7 -> 1440 | F23: 30 | G23: =IF($C23="Weekly",F23,IF($C23="Monthly",F23*12/52,F23/$B$7)) -> 30 | H23: =G23*$B$7 -> 1080 | I23: =E23-H23 -> 360 | J23: Yes | K23: Pre-drinks at home, take a set amount of cash, check student-night deals, walk home or share taxis.
A24: Takeaway (1 a week) | B24: 15 | C24: Weekly | D24: =IF($C24="Weekly",B24,IF($C24="Monthly",B24*12/52,B24/$B$7)) -> 15 | E24: =D24*$B$7 -> 540 | F24: 10 | G24: =IF($C24="Weekly",F24,IF($C24="Monthly",F24*12/52,F24/$B$7)) -> 10 | H24: =G24*$B$7 -> 360 | I24: =E24-H24 -> 180 | J24: Yes | K24: ASSUMPTION: £15 per takeaway. Collect instead of delivery, use student discounts, or make a 'fakeaway'.
A25: Transport | B25: 12.5 | C25: Weekly | D25: =IF($C25="Weekly",B25,IF($C25="Monthly",B25*12/52,B25/$B$7)) -> 12.5 | E25: =D25*$B$7 -> 450 | F25: 12.5 | G25: =IF($C25="Weekly",F25,IF($C25="Monthly",F25*12/52,F25/$B$7)) -> 12.5 | H25: =G25*$B$7 -> 450 | I25: =E25-H25 -> 0 | J25: Yes | K25: Your range of £10–15, so I used the middle. Look at First Bus student tickets/passes and walk when you can.
A26: Toiletries & misc | B26: 5 | C26: Weekly | D26: =IF($C26="Weekly",B26,IF($C26="Monthly",B26*12/52,B26/$B$7)) -> 5 | E26: =D26*$B$7 -> 180 | F26: 5 | G26: =IF($C26="Weekly",F26,IF($C26="Monthly",F26*12/52,F26/$B$7)) -> 5 | H26: =G26*$B$7 -> 180 | I26: =E26-H26 -> 0 | J26: Yes | K26: ASSUMPTION: you didn't list this. Covers toiletries, printing and small stationery.
A27: Google + Apple subscriptions | B27: 6 | C27: Monthly | D27: =IF($C27="Weekly",B27,IF($C27="Monthly",B27*12/52,B27/$B$7)) -> 1.3846154 | E27: =D27*$B$7 -> 49.846154 | F27: 6 | G27: =IF($C27="Weekly",F27,IF($C27="Monthly",F27*12/52,F27/$B$7)) -> 1.3846154 | H27: =G27*$B$7 -> 49.846154 | I27: =E27-H27 -> 0 | J27: No | K27: Your figure. Check student plans and cancel anything you haven't used in a month.
A28: Gym membership | B28: 400 | C28: Per period | D28: =IF($C28="Weekly",B28,IF($C28="Monthly",B28*12/52,B28/$B$7)) -> 11.111111 | E28: =D28*$B$7 -> 400 | F28: 400 | G28: =IF($C28="Weekly",F28,IF($C28="Monthly",F28*12/52,F28/$B$7)) -> 11.111111 | H28: =G28*$B$7 -> 400 | I28: =E28-H28 -> 0 | J28: No | K28: Your figure: £400 for the year. If already paid, set to 0 and lower the SFE figure by what's already gone.
A29: One-offs (Christmas gifts, books, haircuts, clothes) | B29: 150 | C29: Per period | D29: =IF($C29="Weekly",B29,IF($C29="Monthly",B29*12/52,B29/$B$7)) -> 4.1666667 | E29: =D29*$B$7 -> 150 | F29: 150 | G29: =IF($C29="Weekly",F29,IF($C29="Monthly",F29*12/52,F29/$B$7)) -> 4.1666667 | H29: =G29*$B$7 -> 150 | I29: =E29-H29 -> 0 | J29: No | K29: ASSUMPTION: £150 buffer for the year. Change it if you know your plans.
A30: Total spending | D30: =SUM(D20:D29) -> 190.16239 | E30: =SUM(E20:E29) -> 6845.8462 | G30: =SUM(G20:G29) -> 145.16239 | H30: =SUM(H20:H29) -> 5225.8462 | I30: =SUM(I20:I29) -> 1620
A32: Summary
B33: Current habits | C33: Suggested plan
A34: Income per week | B34: =$D$16 -> 190.66667 | C34: =$D$16 -> 190.66667
A35: Spending per week | B35: =D30 -> 190.16239 | C35: =G30 -> 145.16239
A36: Left over per week | B36: =B34-B35 -> 0.5042735 | C36: =C34-C35 -> 45.504274
A37: Savings target per week | B37: =$B$8 -> 25 | C37: =$B$8 -> 25
A38: Spare after savings per week | B38: =B36-B37 -> -24.495726 | C38: =C36-C37 -> 20.504274
A39: Left over by June | B39: =B36*$B$7 -> 18.153846 | C39: =C36*$B$7 -> 1638.1538
A40: Projected savings by June | B40: =MAX(0,MIN(B36,$B$8))*$B$7 -> 18.153846 | C40: =MAX(0,MIN(C36,$B$8))*$B$7 -> 900
A41: Status | B41: =IF(B38>=0,"On track",IF(B36>=0,"Can't hit savings target","Overspending")) -> Can't hit savings target | C41: =IF(C38>=0,"On track",IF(C36>=0,"Can't hit savings target","Overspending")) -> On track

Sheet Weekly Tracker
A1: Weekly Spending Tracker
A2: Each Sunday, type what you actually spent in the blue cells. A cell turns red when it goes over that category's limit. Fixed costs (subscriptions, gym, one-offs) are left out because they're already budgeted.
B4: Weekly limits | C4: Groceries | D4: Laundry | E4: Coffee | F4: Nights out | G4: Takeaway | H4: Transport | I4: Toiletries & misc | J4: Total
B5: ="Plan: "&Budget!$B$9 -> Plan: Suggested | C5: =IF(Budget!$B$9="Current",Budget!$D$20,Budget!$G$20) -> 55 | D5: =IF(Budget!$B$9="Current",Budget!$D$21,Budget!$G$21) -> 7 | E5: =IF(Budget!$B$9="Current",Budget!$D$22,Budget!$G$22) -> 9 | F5: =IF(Budget!$B$9="Current",Budget!$D$23,Budget!$G$23) -> 30 | G5: =IF(Budget!$B$9="Current",Budget!$D$24,Budget!$G$24) -> 10 | H5: =IF(Budget!$B$9="Current",Budget!$D$25,Budget!$G$25) -> 12.5 | I5: =IF(Budget!$B$9="Current",Budget!$D$26,Budget!$G$26) -> 5 | J5: =SUM(C5:I5) -> 128.5
A7: Example | B7: (how a week looks) | C7: 52.3 | D7: 7 | E7: 12 | F7: 35 | G7: 9.5 | H7: 11 | I7: 3.2 | J7: =SUM(C7:I7) -> 130 | K7: =$J$5 -> 128.5 | L7: =K7-J7 -> -1.5
A9: Week | B9: Week starting | C9: Groceries | D9: Laundry | E9: Coffee | F9: Nights out | G9: Takeaway | H9: Transport | I9: Toiletries & misc | J9: Total spent | K9: Weekly limit | L9: Under / (over) | M9: Running total saved
A10: 1 | B10: =IF(A10>Budget!$B$7,"",Budget!$B$5+(A10-1)*7) -> 46300 | J10: =IF(COUNT(C10:I10)=0,"",SUM(C10:I10)) | K10: =IF(B10="","",$J$5) -> 128.5 | L10: =IF(J10="","",K10-J10) | M10: =IF(L10="","",SUM($L$10:L10))
A11: 2 | B11: =IF(A11>Budget!$B$7,"",Budget!$B$5+(A11-1)*7) -> 46307 | J11: =IF(COUNT(C11:I11)=0,"",SUM(C11:I11)) | K11: =IF(B11="","",$J$5) -> 128.5 | L11: =IF(J11="","",K11-J11) | M11: =IF(L11="","",SUM($L$10:L11))
A12: 3 | B12: =IF(A12>Budget!$B$7,"",Budget!$B$5+(A12-1)*7) -> 46314 | J12: =IF(COUNT(C12:I12)=0,"",SUM(C12:I12)) | K12: =IF(B12="","",$J$5) -> 128.5 | L12: =IF(J12="","",K12-J12) | M12: =IF(L12="","",SUM($L$10:L12))
A13: 4 | B13: =IF(A13>Budget!$B$7,"",Budget!$B$5+(A13-1)*7) -> 46321 | J13: =IF(COUNT(C13:I13)=0,"",SUM(C13:I13)) | K13: =IF(B13="","",$J$5) -> 128.5 | L13: =IF(J13="","",K13-J13) | M13: =IF(L13="","",SUM($L$10:L13))
A14: 5 | B14: =IF(A14>Budget!$B$7,"",Budget!$B$5+(A14-1)*7) -> 46328 | J14: =IF(COUNT(C14:I14)=0,"",SUM(C14:I14)) | K14: =IF(B14="","",$J$5) -> 128.5 | L14: =IF(J14="","",K14-J14) | M14: =IF(L14="","",SUM($L$10:L14))
A15: 6 | B15: =IF(A15>Budget!$B$7,"",Budget!$B$5+(A15-1)*7) -> 46335 | J15: =IF(COUNT(C15:I15)=0,"",SUM(C15:I15)) | K15: =IF(B15="","",$J$5) -> 128.5 | L15: =IF(J15="","",K15-J15) | M15: =IF(L15="","",SUM($L$10:L15))
A16: 7 | B16: =IF(A16>Budget!$B$7,"",Budget!$B$5+(A16-1)*7) -> 46342 | J16: =IF(COUNT(C16:I16)=0,"",SUM(C16:I16)) | K16: =IF(B16="","",$J$5) -> 128.5 | L16: =IF(J16="","",K16-J16) | M16: =IF(L16="","",SUM($L$10:L16))
A17: 8 | B17: =IF(A17>Budget!$B$7,"",Budget!$B$5+(A17-1)*7) -> 46349 | J17: =IF(COUNT(C17:I17)=0,"",SUM(C17:I17)) | K17: =IF(B17="","",$J$5) -> 128.5 | L17: =IF(J17="","",K17-J17) | M17: =IF(L17="","",SUM($L$10:L17))
A18: 9 | B18: =IF(A18>Budget!$B$7,"",Budget!$B$5+(A18-1)*7) -> 46356 | J18: =IF(COUNT(C18:I18)=0,"",SUM(C18:I18)) | K18: =IF(B18="","",$J$5) -> 128.5 | L18: =IF(J18="","",K18-J18) | M18: =IF(L18="","",SUM($L$10:L18))
A19: 10 | B19: =IF(A19>Budget!$B$7,"",Budget!$B$5+(A19-1)*7) -> 46363 | J19: =IF(COUNT(C19:I19)=0,"",SUM(C19:I19)) | K19: =IF(B19="","",$J$5) -> 128.5 | L19: =IF(J19="","",K19-J19) | M19: =IF(L19="","",SUM($L$10:L19))
A20: 11 | B20: =IF(A20>Budget!$B$7,"",Budget!$B$5+(A20-1)*7) -> 46370 | J20: =IF(COUNT(C20:I20)=0,"",SUM(C20:I20)) | K20: =IF(B20="","",$J$5) -> 128.5 | L20: =IF(J20="","",K20-J20) | M20: =IF(L20="","",SUM($L$10:L20))
A21: 12 | B21: =IF(A21>Budget!$B$7,"",Budget!$B$5+(A21-1)*7) -> 46377 | J21: =IF(COUNT(C21:I21)=0,"",SUM(C21:I21)) | K21: =IF(B21="","",$J$5) -> 128.5 | L21: =IF(J21="","",K21-J21) | M21: =IF(L21="","",SUM($L$10:L21))
... A49: 40 | B49: =IF(A49>Budget!$B$7,"",Budget!$B$5+(A49-1)*7) | J49: =IF(COUNT(C49:I49)=0,"",SUM(C49:I49)) | K49: =IF(B49="","",$J$5) | L49: =IF(J49="","",K49-J49) | M49: =IF(L49="","",SUM($L$10:L49))
A50: Total | C50: =SUM(C10:C49) -> 0 | D50: =SUM(D10:D49) -> 0 | E50: =SUM(E10:E49) -> 0 | F50: =SUM(F10:F49) -> 0 | G50: =SUM(G10:G49) -> 0 | H50: =SUM(H10:H49) -> 0 | I50: =SUM(I10:I49) -> 0 | J50: =SUM(J10:J49) -> 0 | L50: =SUM(L10:L49) -> 0
A51: Avg / week | C51: =IF(COUNT(J10:J49)=0,"",C50/COUNT(J10:J49)) | D51: =IF(COUNT(J10:J49)=0,"",D50/COUNT(J10:J49)) | E51: =IF(COUNT(J10:J49)=0,"",E50/COUNT(J10:J49)) | F51: =IF(COUNT(J10:J49)=0,"",F50/COUNT(J10:J49)) | G51: =IF(COUNT(J10:J49)=0,"",G50/COUNT(J10:J49)) | H51: =IF(COUNT(J10:J49)=0,"",H50/COUNT(J10:J49)) | I51: =IF(COUNT(J10:J49)=0,"",I50/COUNT(J10:J49)) | J51: =IF(COUNT(J10:J49)=0,"",J50/COUNT(J10:J49)) | L51: =IF(COUNT(J10:J49)=0,"",L50/COUNT(J10:J49))

Sheet Tips
A1: Where to spend less, and tips for sticking to it
A3: THE BIG PICTURE
A4: Your current habits use almost all of your income. Your lifestyle is affordable, but there's almost nothing spare for emergencies or savings. The Summary on the Budget tab shows the exact figures.
A5: The Suggested plan frees up about £45 a week (about £1,600 by June) without cutting anything completely.
A7: BIGGEST WINS (ranked by money saved)
A8: 1. Groceries (£70 → £55): this is your biggest cost. Aldi and Lidl are usually much cheaper than Sainsbury's or Waitrose, and Bath has both. Batch-cook 2–3 meals on Sunday, plan meals before you shop and use own-brand. Saves about £540 by June.
A9: 2. Coffee (£21 → £9): £3 a day adds up to about £750 by June. A cafetière and a bag of decent coffee costs about £15 and lasts weeks. Keep bought coffee as a treat on 3 days. Saves about £430.
A10: 3. Nights out (£40 → £30): do pre-drinks, take a set amount of cash and leave your card at home, and look for SU or student-night deals. Saves about £360.
A11: 4. Takeaway (£15 → £10): collect instead of delivery (no fees), use student discount apps, or swap every other takeaway for a 'fakeaway' night. Saves about £180.
A12: 5. Laundry (£10 → £7): wash full loads only and skip the dryer by using a clothes airer (about £15). Saves about £110.
A14: HABITS THAT MAKE A BUDGET STICK
A15: • Pay yourself first. When money comes in (each SFE instalment, the grandparents' money), move your savings target into a separate savings pot straight away.
... A27: • Avoid buy-now-pay-later and overdraft creep. A student bank account's interest-free overdraft is a safety net, not income.
